patabase/__init__.py
patabase/empty.py
patabase/mssql.py
patabase/postgres.py
patabase-0.2.2.dist-info/LICENSE
patabase-0.2.2.dist-info/METADATA
patabase-0.2.2.dist-info/WHEEL
patabase-0.2.2.dist-info/top_level.txt
patabase-0.2.2.dist-info/RECORD
