Metadata-Version: 2.1
Name: patabase
Version: 0.2.2
Summary: Simplify DB API usage
Home-page: https://github.com/xurvan/patabase
Author: Xurvan
License: apache-2.0
Download-URL: https://github.com/xurvan/patabase/archive/v0.2.2.zip
Project-URL: Code, https://github.com/xurvan/patabase
Project-URL: Issue tracker, https://github.com/xurvan/patabase/issues
Platform: UNKNOWN
Classifier: Development Status :: 3 - Alpha
Classifier: Intended Audience :: Developers
Classifier: Topic :: Software Development
Classifier: License :: OSI Approved :: Apache Software License
Classifier: Programming Language :: Python :: 3
Requires-Python: >=3.6
